{
  "id": "1386898690844786738",
  "name": "Compact Shulker Box (is full?/is partial?) Sorter",
  "code": "FBS003",
  "reservedCodes": [
    "FBS003"
  ],
  "pastPostThreadIds": [
    "1388316911879848067"
  ],
  "authors": [
    {
      "type": "discord-in-guild",
      "id": "803398149217189950",
      "username": "nvertd",
      "iconURL": "https://cdn.discordapp.com/avatars/803398149217189950/b5bc2649d3bf10ad4d486ab0e3e2c0ab.webp",
      "displayName": "Nvertd"
    },
    {
      "type": "discord-in-guild",
      "id": "656864003242328064",
      "name": "acaciachan",
      "displayName": "金合欢酱喵~ (acaciachan)",
      "iconURL": "https://cdn.discordapp.com/avatars/656864003242328064/65e1c203d9ea0af6509f0754122b45a2.webp",
      "username": "acaciachan"
    }
  ],
  "endorsers": [
    {
      "type": "discord-in-guild",
      "id": "239078039831445504",
      "username": "andrews54757",
      "displayName": "Andrews54757",
      "iconURL": "https://cdn.discordapp.com/avatars/239078039831445504/3cabc63679bd9d8d74073833458570b3.webp"
    }
  ],
  "tags": [
    {
      "id": "1465487113117106203",
      "name": "Recommended"
    },
    {
      "id": "1465490819187212557",
      "name": "Functional"
    },
    {
      "id": "1386421810626695278",
      "name": "isEmpty/isFull"
    }
  ],
  "images": [
    {
      "id": "1386898691721265354",
      "name": "area_render_29.png",
      "contentType": "image/png",
      "url": "https://cdn.discordapp.com/attachments/1386898690844786738/1386898691721265354/area_render_29.png?ex=685b618f&is=685a100f&hm=2035236dd41b321a70997d984f739506f727afd9453ad0c9b2246c1d8c2c40cc&",
      "description": "",
      "canDownload": true,
      "width": 800,
      "height": 774,
      "path": "images/area_render_29.png",
      "source": "MessageAttachment",
      "author": {
        "type": "unknown",
        "username": "andrews54757"
      },
      "timestamp": 1750732815000,
      "hash": "c5ce5c5c5c46a7a98328f377a466e72da1870da269a60ea86bc499c6f2193f88"
    }
  ],
  "attachments": [
    {
      "id": "1386898691948019752",
      "name": "FBS003_nvertd_isfull_v2.litematic",
      "contentType": "unknown",
      "url": "https://cdn.discordapp.com/attachments/1386898690844786738/1386898691948019752/nvertd_isfull_v2.litematic?ex=685b618f&is=685a100f&hm=63013220947de523ab87c1e8dda20d0970e4faa8c0f645439385b51bccc358a1&",
      "description": "",
      "canDownload": true,
      "litematic": {
        "size": "4x3x5",
        "version": "1.17.1"
      },
      "path": "attachments/FBS003_nvertd_isfull_v2.litematic",
      "source": "MessageAttachment",
      "author": {
        "type": "unknown",
        "username": "andrews54757"
      },
      "timestamp": 1750732815000,
      "size": 1206,
      "hash": "d5910c9360eb80d6bb8d94bb5d6134ee20f5be3bc7f40295977829625fc88ebf"
    }
  ],
  "records": {
    "description": "Small device that categorizes boxes by their fill levels at hopperspeed. Can function either as an isFull filter or as an isNotEmpty sorter with modification to the comparator barrel's contents.",
    "features": [
      "Small size (3x3x4).",
      "Hopperspeed (8gt; 9000 boxes/hr).",
      "Works with randomly timed input."
    ],
    "considerations": [],
    "notes": ""
  },
  "references": [
    {
      "type": "dictionaryTerm",
      "term": "Hopper speed",
      "id": "1454937395693879409",
      "url": "https://discord.com/channels/1375556143186837695/1454937395693879409/1454937397304365294",
      "matches": [
        "hopperspeed",
        "Hopperspeed"
      ]
    },
    {
      "type": "dictionaryTerm",
      "term": "Fill Sorter",
      "id": "1454753607604768770",
      "url": "https://discord.com/channels/1375556143186837695/1454753607604768770/1454753609131495434",
      "matches": [
        "isFull"
      ]
    },
    {
      "type": "dictionaryTerm",
      "term": "Gametick",
      "id": "1454753634435858666",
      "url": "https://discord.com/channels/1375556143186837695/1454753634435858666/1454753635690090539",
      "matches": [
        "gt"
      ]
    }
  ],
  "author_references": [],
  "post": {
    "forumId": "1375559651579527208",
    "threadId": "1388316911879848067",
    "continuingMessageIds": [
      "1388316914001907733"
    ],
    "threadURL": "https://discord.com/channels/1375556143186837695/1388316911879848067",
    "attachmentMessageId": "1388177732633886753",
    "uploadMessageId": "1388177726396960830"
  },
  "archivedAt": 1750732870769,
  "updatedAt": 1750732870769,
  "num_comments": 0
}