{
  "id": "1387997827422097460",
  "name": "1wt Variable Display",
  "code": "OD002",
  "reservedCodes": [
    "OD002"
  ],
  "pastPostThreadIds": [
    "1388317374729551995"
  ],
  "authors": [
    {
      "type": "discord-in-guild",
      "id": "889866137184137238",
      "displayName": "bipim",
      "username": "bipim",
      "iconURL": "https://cdn.discordapp.com/avatars/889866137184137238/7e7a059e3e137003a2abe1a91499f786.webp"
    }
  ],
  "endorsers": [
    {
      "type": "discord-in-guild",
      "id": "239078039831445504",
      "username": "andrews54757",
      "displayName": "Andrews54757",
      "iconURL": "https://cdn.discordapp.com/avatars/239078039831445504/3cabc63679bd9d8d74073833458570b3.webp"
    }
  ],
  "tags": [
    {
      "id": "1465491092089868288",
      "name": "Functional"
    },
    {
      "id": "1465487299406991530",
      "name": "Recommended"
    },
    {
      "id": "1386201827846127667",
      "name": "Reliable Collection"
    }
  ],
  "images": [
    {
      "id": "1387997827820683385",
      "name": "area_render_72_.png",
      "contentType": "image/png",
      "url": "https://cdn.discordapp.com/attachments/1387997827422097460/1387997827820683385/area_render_72_.png?ex=685f6135&is=685e0fb5&hm=c987c3de3b32be57e0f97f84933c72844ec61316875dd8494b6f8ad080e515e1&",
      "description": "",
      "canDownload": true,
      "width": 800,
      "height": 662,
      "path": "images/area_render_72_.png",
      "source": "MessageAttachment",
      "author": {
        "type": "unknown",
        "username": "andrews54757"
      },
      "timestamp": 1750994869000,
      "hash": "cfa540112a7962412c2f43968cd7f5949006a4c487a154244d0201bb865a2d68"
    }
  ],
  "attachments": [
    {
      "id": "1387997828160163901",
      "name": "OD002_vardisp_1wt.litematic",
      "contentType": "unknown",
      "url": "https://cdn.discordapp.com/attachments/1387997827422097460/1387997828160163901/vardisp_1wt.litematic?ex=685f6135&is=685e0fb5&hm=e17277397afea20645261b3a332653e3e954c21c88a24af09639eb52d9412bcb&",
      "description": "",
      "canDownload": true,
      "litematic": {
        "size": "1x5x6",
        "version": "1.20.2"
      },
      "path": "attachments/OD002_vardisp_1wt.litematic",
      "source": "MessageAttachment",
      "author": {
        "type": "unknown",
        "username": "andrews54757"
      },
      "timestamp": 1750994869000,
      "size": 1203,
      "hash": "3dfc6aa5a2ba548f95dcb157f2b08e0f599cd419d8582a0c04d4516ddd9d85cd"
    }
  ],
  "records": {
    "description": "Displays a box thrown by the player into the collection hopper. The old box is collected and put into the chest.",
    "features": [
      "Small design, only 6x5 blocks"
    ],
    "considerations": [],
    "notes": "Concept by daisy_pig"
  },
  "references": [],
  "author_references": [],
  "post": {
    "forumId": "1375561629378416740",
    "threadId": "1388317374729551995",
    "continuingMessageIds": [
      "1388317379720777795"
    ],
    "threadURL": "https://discord.com/channels/1375556143186837695/1388317374729551995",
    "attachmentMessageId": "1388178310378422426",
    "uploadMessageId": "1388178304405733528"
  },
  "archivedAt": 1751013871094,
  "updatedAt": 1751013871094,
  "num_comments": 0
}